<?xml version="1.0" encoding="utf-8"?>
<odoo>
    <!-- Finance PPM Go-Live Checklist Items -->

    <!-- Section 1: Data & System Readiness (6 items) -->
    <record id="item_odoo_accessible" model="ipai.finance.ppm.golive.item">
        <field name="name">Odoo CE 18 accessible at http://159.223.75.148:8071</field>
        <field name="section_id" ref="section_data_system"/>
        <field name="sequence">10</field>
        <field name="is_critical" eval="True"/>
        <field name="description">Verify Odoo web interface loads and responds within 3 seconds</field>
    </record>

    <record id="item_postgresql_healthy" model="ipai.finance.ppm.golive.item">
        <field name="name">PostgreSQL (odoo_accounting) healthy</field>
        <field name="section_id" ref="section_data_system"/>
        <field name="sequence">20</field>
        <field name="is_critical" eval="True"/>
        <field name="description">Database accessible via psql, no stuck transactions, query response time &lt; 100ms</field>
    </record>

    <record id="item_supabase_accessible" model="ipai.finance.ppm.golive.item">
        <field name="name">Supabase project (spdtwktxdalcfigzeqrz) accessible</field>
        <field name="section_id" ref="section_data_system"/>
        <field name="sequence">30</field>
        <field name="description">Supabase dashboard accessible, RLS policies active, API responding</field>
    </record>

    <record id="item_n8n_accessible" model="ipai.finance.ppm.golive.item">
        <field name="name">n8n accessible at https://ipa.insightpulseai.com</field>
        <field name="section_id" ref="section_data_system"/>
        <field name="sequence">40</field>
        <field name="is_critical" eval="True"/>
        <field name="description">n8n UI accessible, API key valid, webhooks responding</field>
    </record>

    <record id="item_mattermost_webhook" model="ipai.finance.ppm.golive.item">
        <field name="name">Mattermost webhook configured</field>
        <field name="section_id" ref="section_data_system"/>
        <field name="sequence">50</field>
        <field name="description">Test message sent successfully to Finance SSC channel</field>
    </record>

    <record id="item_docker_services" model="ipai.finance.ppm.golive.item">
        <field name="name">All 3 Docker services running (odoo-accounting, db, nginx-proxy)</field>
        <field name="section_id" ref="section_data_system"/>
        <field name="sequence">60</field>
        <field name="is_critical" eval="True"/>
        <field name="description">Docker ps shows all containers healthy with uptime &gt; 5 minutes</field>
    </record>

    <!-- Section 2: Finance PPM Module Readiness (8 items) -->
    <record id="item_oca_modules" model="ipai.finance.ppm.golive.item">
        <field name="name">8 OCA modules state='installed'</field>
        <field name="section_id" ref="section_module"/>
        <field name="sequence">10</field>
        <field name="is_critical" eval="True"/>
        <field name="description">Verify: account_financial_report, account_asset_management, account_cutoff_accrual_order_base, account_move_reversal, hr_expense_advance_clearing, account_multicurrency_revaluation, account_intercompany, project_wip</field>
    </record>

    <record id="item_ipai_modules" model="ipai.finance.ppm.golive.item">
        <field name="name">13 IPAI modules state='installed'</field>
        <field name="section_id" ref="section_module"/>
        <field name="sequence">20</field>
        <field name="is_critical" eval="True"/>
        <field name="description">Verify: ipai_finance_ppm, ipai_ppm_a1, ipai_close_orchestration, ipai_clarity_ppm_parity, and 9 supporting modules</field>
    </record>

    <record id="item_finance_ppm_menu" model="ipai.finance.ppm.golive.item">
        <field name="name">ipai_finance_ppm visible in Apps menu</field>
        <field name="section_id" ref="section_module"/>
        <field name="sequence">30</field>
        <field name="description">Finance PPM module appears in Odoo Apps list with correct icon and description</field>
    </record>

    <record id="item_a1_menu" model="ipai.finance.ppm.golive.item">
        <field name="name">ipai_ppm_a1 (A1 Control Center) menu accessible</field>
        <field name="section_id" ref="section_module"/>
        <field name="sequence">40</field>
        <field name="description">A1 Control Center menu visible, dashboard loads without errors</field>
    </record>

    <record id="item_bir_schedule" model="ipai.finance.ppm.golive.item">
        <field name="name">BIR schedule synced (8 forms loaded)</field>
        <field name="section_id" ref="section_module"/>
        <field name="sequence">50</field>
        <field name="is_critical" eval="True"/>
        <field name="description">BIR forms: 1601-C, 0619-E, 2550Q, 1702-RT, 1601-EQ, 1601-FQ loaded with correct deadlines</field>
    </record>

    <record id="item_logframe_visible" model="ipai.finance.ppm.golive.item">
        <field name="name">Logframe visible in Finance PPM dashboard</field>
        <field name="section_id" ref="section_module"/>
        <field name="sequence">60</field>
        <field name="description">Logframe levels: Goal → Outcome → IM1/IM2 → Outputs → Activities correctly displayed</field>
    </record>

    <record id="item_echarts_loads" model="ipai.finance.ppm.golive.item">
        <field name="name">ECharts dashboard loads without JS errors</field>
        <field name="section_id" ref="section_module"/>
        <field name="sequence">70</field>
        <field name="description">Browser console shows no errors, all 4 charts render correctly</field>
    </record>

    <record id="item_user_roles" model="ipai.finance.ppm.golive.item">
        <field name="name">User roles configured (Supervisor, Director, CFO)</field>
        <field name="section_id" ref="section_module"/>
        <field name="sequence">80</field>
        <field name="description">Security groups assigned, access control lists verified</field>
    </record>

    <!-- Section 3: AFC (Financial Close) Go-Live Check (8 items) -->
    <record id="item_afc_workstream" model="ipai.finance.ppm.golive.item">
        <field name="name">AFC workstream configured in A1</field>
        <field name="section_id" ref="section_afc"/>
        <field name="sequence">10</field>
        <field name="is_critical" eval="True"/>
        <field name="description">AFC (Accounting &amp; Finance Close) workstream visible in A1 Control Center</field>
    </record>

    <record id="item_closing_template" model="ipai.finance.ppm.golive.item">
        <field name="name">December 2025 closing cycle created (33 tasks)</field>
        <field name="section_id" ref="section_afc"/>
        <field name="sequence">20</field>
        <field name="is_critical" eval="True"/>
        <field name="description">33 closing tasks created with correct due dates and assignments</field>
    </record>

    <record id="item_raci_assigned" model="ipai.finance.ppm.golive.item">
        <field name="name">RACI assignments for closing tasks</field>
        <field name="section_id" ref="section_afc"/>
        <field name="sequence">30</field>
        <field name="description">Responsible, Accountable, Consulted, Informed roles assigned to all tasks</field>
    </record>

    <record id="item_reconciliation" model="ipai.finance.ppm.golive.item">
        <field name="name">Bank reconciliation workflow tested</field>
        <field name="section_id" ref="section_afc"/>
        <field name="sequence">40</field>
        <field name="description">Bank statement import, matching rules, manual reconciliation tested end-to-end</field>
    </record>

    <record id="item_gl_recon" model="ipai.finance.ppm.golive.item">
        <field name="name">GL reconciliation workflow tested</field>
        <field name="section_id" ref="section_afc"/>
        <field name="sequence">50</field>
        <field name="description">Account reconciliation, variance analysis, approval workflow tested</field>
    </record>

    <record id="item_je_posting" model="ipai.finance.ppm.golive.item">
        <field name="name">JE posting and approval tested</field>
        <field name="section_id" ref="section_afc"/>
        <field name="sequence">60</field>
        <field name="description">Journal entry creation, review, approval, posting workflow tested</field>
    </record>

    <record id="item_period_lock" model="ipai.finance.ppm.golive.item">
        <field name="name">Period lock mechanism tested</field>
        <field name="section_id" ref="section_afc"/>
        <field name="sequence">70</field>
        <field name="description">Month-end lock prevents posting to closed periods</field>
    </record>

    <record id="item_closing_sla" model="ipai.finance.ppm.golive.item">
        <field name="name">Closing SLA &lt;= 5 business days validated</field>
        <field name="section_id" ref="section_afc"/>
        <field name="sequence">80</field>
        <field name="is_critical" eval="True"/>
        <field name="description">Historical test cycle completed in 5 business days or less</field>
    </record>

    <!-- Section 4: STC (Tax Compliance) Go-Live Check (7 items) -->
    <record id="item_stc_workstream" model="ipai.finance.ppm.golive.item">
        <field name="name">STC workstream configured in A1</field>
        <field name="section_id" ref="section_stc"/>
        <field name="sequence">10</field>
        <field name="is_critical" eval="True"/>
        <field name="description">STC (Statutory Tax Compliance) workstream visible in A1 Control Center</field>
    </record>

    <record id="item_bir_1601c" model="ipai.finance.ppm.golive.item">
        <field name="name">BIR 1601-C auto-generation tested</field>
        <field name="section_id" ref="section_stc"/>
        <field name="sequence">20</field>
        <field name="is_critical" eval="True"/>
        <field name="description">Monthly withholding tax return generated with ≥98% accuracy</field>
    </record>

    <record id="item_bir_2550q" model="ipai.finance.ppm.golive.item">
        <field name="name">BIR 2550Q auto-generation tested</field>
        <field name="section_id" ref="section_stc"/>
        <field name="sequence">30</field>
        <field name="is_critical" eval="True"/>
        <field name="description">Quarterly income tax return generated with ≥98% accuracy</field>
    </record>

    <record id="item_bir_tasks" model="ipai.finance.ppm.golive.item">
        <field name="name">3-task workflow per BIR form (Prep → Review → Approval)</field>
        <field name="section_id" ref="section_stc"/>
        <field name="sequence">40</field>
        <field name="description">Each BIR form creates 3 tasks: preparation, review, approval with correct due dates</field>
    </record>

    <record id="item_bir_alerts" model="ipai.finance.ppm.golive.item">
        <field name="name">7-day deadline alerts working</field>
        <field name="section_id" ref="section_stc"/>
        <field name="sequence">50</field>
        <field name="description">n8n workflow sends Mattermost alerts 7 days before BIR deadlines</field>
    </record>

    <record id="item_multi_employee" model="ipai.finance.ppm.golive.item">
        <field name="name">8-employee BIR consolidation tested</field>
        <field name="section_id" ref="section_stc"/>
        <field name="sequence">60</field>
        <field name="is_critical" eval="True"/>
        <field name="description">BIR forms consolidated for: RIM, CKVC, BOM, JPAL, JLI, JAP, LAS, RMQB</field>
    </record>

    <record id="item_tax_accuracy" model="ipai.finance.ppm.golive.item">
        <field name="name">Tax calculation accuracy ≥98%</field>
        <field name="section_id" ref="section_stc"/>
        <field name="sequence">70</field>
        <field name="is_critical" eval="True"/>
        <field name="description">Compared against manual calculations, variance &lt; 2%</field>
    </record>

    <!-- Section 5: Control Room (AI/Automation) Go-Live Check (6 items) -->
    <record id="item_n8n_workflows" model="ipai.finance.ppm.golive.item">
        <field name="name">3 n8n workflows active (bir_deadline_alert, task_escalation, monthly_report)</field>
        <field name="section_id" ref="section_control_room"/>
        <field name="sequence">10</field>
        <field name="is_critical" eval="True"/>
        <field name="description">All 3 workflows imported successfully, test execution passes</field>
    </record>

    <record id="item_task_bus" model="ipai.finance.ppm.golive.item">
        <field name="name">Supabase task_queue operational</field>
        <field name="section_id" ref="section_control_room"/>
        <field name="sequence">20</field>
        <field name="description">route_and_enqueue() RPC tested, no stuck tasks older than 5 minutes</field>
    </record>

    <record id="item_mattermost_notify" model="ipai.finance.ppm.golive.item">
        <field name="name">Mattermost notifications tested end-to-end</field>
        <field name="section_id" ref="section_control_room"/>
        <field name="sequence">30</field>
        <field name="description">Deadline alerts, task escalations, monthly summaries delivered successfully</field>
    </record>

    <record id="item_escalation" model="ipai.finance.ppm.golive.item">
        <field name="name">Escalation logic tested (3 days before deadline)</field>
        <field name="section_id" ref="section_control_room"/>
        <field name="sequence">40</field>
        <field name="description">Overdue tasks auto-escalate to Finance Director with correct message format</field>
    </record>

    <record id="item_idempotency" model="ipai.finance.ppm.golive.item">
        <field name="name">Idempotency keys preventing duplicate tasks</field>
        <field name="section_id" ref="section_control_room"/>
        <field name="sequence">50</field>
        <field name="description">Re-running workflows does not create duplicate BIR tasks or notifications</field>
    </record>

    <record id="item_lineage" model="ipai.finance.ppm.golive.item">
        <field name="name">Workflow lineage tracked in Supabase</field>
        <field name="section_id" ref="section_control_room"/>
        <field name="sequence">60</field>
        <field name="description">cr_lineage table populated with upstream/downstream dependencies</field>
    </record>

    <!-- Section 6: Notion-AI Parity Check (5 items) -->
    <record id="item_notion_workspace" model="ipai.finance.ppm.golive.item">
        <field name="name">Notion-AI workspace sync configured</field>
        <field name="section_id" ref="section_notion_parity"/>
        <field name="sequence">10</field>
        <field name="description">Notion integration token valid, workspace accessible</field>
    </record>

    <record id="item_spec_bundles" model="ipai.finance.ppm.golive.item">
        <field name="name">Spec bundles synced from Notion to /spec/</field>
        <field name="section_id" ref="section_notion_parity"/>
        <field name="sequence">20</field>
        <field name="description">All spec bundles (constitution, prd, plan, tasks) exported to repo</field>
    </record>

    <record id="item_task_sync" model="ipai.finance.ppm.golive.item">
        <field name="name">Notion tasks synced to Odoo project tasks</field>
        <field name="section_id" ref="section_notion_parity"/>
        <field name="sequence">30</field>
        <field name="description">Bidirectional sync: Notion → Odoo, status updates reflect in both systems</field>
    </record>

    <record id="item_knowledge_base" model="ipai.finance.ppm.golive.item">
        <field name="name">Knowledge base articles accessible from Odoo</field>
        <field name="section_id" ref="section_notion_parity"/>
        <field name="sequence">40</field>
        <field name="description">Notion wiki pages linked in Odoo help menu</field>
    </record>

    <record id="item_meeting_notes" model="ipai.finance.ppm.golive.item">
        <field name="name">Meeting notes auto-created in Notion</field>
        <field name="section_id" ref="section_notion_parity"/>
        <field name="sequence">50</field>
        <field name="description">n8n workflow creates Notion page for month-end closing meetings</field>
    </record>

    <!-- Section 7: Audit & Compliance Check (6 items) -->
    <record id="item_audit_trail" model="ipai.finance.ppm.golive.item">
        <field name="name">Audit trail enabled on all financial transactions</field>
        <field name="section_id" ref="section_audit_compliance"/>
        <field name="sequence">10</field>
        <field name="is_critical" eval="True"/>
        <field name="description">All journal entries, approvals, period locks tracked with timestamps and user IDs</field>
    </record>

    <record id="item_rls_policies" model="ipai.finance.ppm.golive.item">
        <field name="name">Supabase RLS policies active and tested</field>
        <field name="section_id" ref="section_audit_compliance"/>
        <field name="sequence">20</field>
        <field name="is_critical" eval="True"/>
        <field name="description">Row-Level Security prevents unauthorized access to finance_ppm tables</field>
    </record>

    <record id="item_user_permissions" model="ipai.finance.ppm.golive.item">
        <field name="name">Odoo user permissions validated by role</field>
        <field name="section_id" ref="section_audit_compliance"/>
        <field name="sequence">30</field>
        <field name="description">Supervisor, Director, CFO roles have correct access levels tested</field>
    </record>

    <record id="item_backup_verified" model="ipai.finance.ppm.golive.item">
        <field name="name">Database backups verified and restorable</field>
        <field name="section_id" ref="section_audit_compliance"/>
        <field name="sequence">40</field>
        <field name="is_critical" eval="True"/>
        <field name="description">Daily backups tested, restore time &lt; 15 minutes</field>
    </record>

    <record id="item_error_logging" model="ipai.finance.ppm.golive.item">
        <field name="name">Error logging and monitoring active</field>
        <field name="section_id" ref="section_audit_compliance"/>
        <field name="sequence">50</field>
        <field name="description">Odoo logs, n8n logs, PostgreSQL logs centralized and searchable</field>
    </record>

    <record id="item_ph_compliance" model="ipai.finance.ppm.golive.item">
        <field name="name">PH tax compliance validated (8 BIR forms)</field>
        <field name="section_id" ref="section_audit_compliance"/>
        <field name="sequence">60</field>
        <field name="is_critical" eval="True"/>
        <field name="description">All 8 BIR forms match official format and calculation rules</field>
    </record>

    <!-- Section 8: Operational Check (7 items) -->
    <record id="item_user_training" model="ipai.finance.ppm.golive.item">
        <field name="name">User training completed (Supervisor, Director, CFO)</field>
        <field name="section_id" ref="section_operational"/>
        <field name="sequence">10</field>
        <field name="is_critical" eval="True"/>
        <field name="description">1-hour training session completed, all users can perform key tasks</field>
    </record>

    <record id="item_runbook" model="ipai.finance.ppm.golive.item">
        <field name="name">Operations runbook published and accessible</field>
        <field name="section_id" ref="section_operational"/>
        <field name="sequence">20</field>
        <field name="description">Runbook covers: month-end closing, BIR filing, escalations, rollback procedures</field>
    </record>

    <record id="item_support_channel" model="ipai.finance.ppm.golive.item">
        <field name="name">Support channel configured in Mattermost</field>
        <field name="section_id" ref="section_operational"/>
        <field name="sequence">30</field>
        <field name="description">Finance SSC support channel created, response SLA &lt; 2 hours</field>
    </record>

    <record id="item_sla_documented" model="ipai.finance.ppm.golive.item">
        <field name="name">SLAs documented and agreed (closing ≤5 days, BIR on-time)</field>
        <field name="section_id" ref="section_operational"/>
        <field name="sequence">40</field>
        <field name="description">Service level agreements signed by CFO</field>
    </record>

    <record id="item_monitoring_dashboard" model="ipai.finance.ppm.golive.item">
        <field name="name">Monitoring dashboard accessible to Finance Director</field>
        <field name="section_id" ref="section_operational"/>
        <field name="sequence">50</field>
        <field name="description">ECharts dashboard shows: BIR deadlines, completion %, at-risk tasks, late filings</field>
    </record>

    <record id="item_rollback_tested" model="ipai.finance.ppm.golive.item">
        <field name="name">Rollback procedure tested successfully</field>
        <field name="section_id" ref="section_operational"/>
        <field name="sequence">60</field>
        <field name="is_critical" eval="True"/>
        <field name="description">Rollback to previous version completed in &lt; 15 minutes</field>
    </record>

    <record id="item_incident_response" model="ipai.finance.ppm.golive.item">
        <field name="name">Incident response plan documented</field>
        <field name="section_id" ref="section_operational"/>
        <field name="sequence">70</field>
        <field name="description">Plan covers: system outage, data corruption, BIR deadline miss scenarios</field>
    </record>

    <!-- Section 9: Official Go-Live Criteria (6 items) -->
    <record id="item_100pct_complete" model="ipai.finance.ppm.golive.item">
        <field name="name">All previous sections 100% complete</field>
        <field name="section_id" ref="section_golive_criteria"/>
        <field name="sequence">10</field>
        <field name="is_critical" eval="True"/>
        <field name="description">All 53 checklist items above marked as complete with evidence</field>
    </record>

    <record id="item_smoke_test" model="ipai.finance.ppm.golive.item">
        <field name="name">End-to-end smoke test passed</field>
        <field name="section_id" ref="section_golive_criteria"/>
        <field name="sequence">20</field>
        <field name="is_critical" eval="True"/>
        <field name="description">Complete workflow: create cycle → assign tasks → close period → generate BIR → notify</field>
    </record>

    <record id="item_visual_parity" model="ipai.finance.ppm.golive.item">
        <field name="name">Visual parity thresholds met (SSIM ≥0.97 mobile, ≥0.98 desktop)</field>
        <field name="section_id" ref="section_golive_criteria"/>
        <field name="sequence">30</field>
        <field name="description">Screenshots compared against baseline, all routes pass threshold</field>
    </record>

    <record id="item_performance" model="ipai.finance.ppm.golive.item">
        <field name="name">Performance benchmarks met (P95 ≤ 30s OCR, &lt;3s UI load)</field>
        <field name="section_id" ref="section_golive_criteria"/>
        <field name="sequence">40</field>
        <field name="description">OCR backend P95 latency ≤30s, Odoo UI loads in &lt;3s</field>
    </record>

    <record id="item_cfo_signoff" model="ipai.finance.ppm.golive.item">
        <field name="name">CFO sign-off obtained (PDF exported and signed)</field>
        <field name="section_id" ref="section_golive_criteria"/>
        <field name="sequence">50</field>
        <field name="is_critical" eval="True"/>
        <field name="description">CFO approves go-live checklist with official signature on PDF report</field>
    </record>

    <record id="item_deployment_log" model="ipai.finance.ppm.golive.item">
        <field name="name">Deployment log archived (GitHub Actions run + Mattermost notification)</field>
        <field name="section_id" ref="section_golive_criteria"/>
        <field name="sequence">60</field>
        <field name="description">CI/CD logs, health check results, deployment timestamp saved for audit</field>
    </record>
</odoo>
